ovos_skill_cmd/LICENSE.txt
ovos_skill_cmd/MANIFEST.in
ovos_skill_cmd/README.md
ovos_skill_cmd/__init__.py
ovos_skill_cmd/requirements.txt
ovos_skill_cmd/version.py
ovos_skill_cmd/locale/ca-es/Run.voc
ovos_skill_cmd/locale/ca-es/running.dialog
ovos_skill_cmd/locale/ca-es/skill.json
ovos_skill_cmd/locale/da/Run.voc
ovos_skill_cmd/locale/da/running.dialog
ovos_skill_cmd/locale/da/skill.json
ovos_skill_cmd/locale/de-de/Run.voc
ovos_skill_cmd/locale/de-de/running.dialog
ovos_skill_cmd/locale/de-de/skill.json
ovos_skill_cmd/locale/en-us/Run.voc
ovos_skill_cmd/locale/en-us/running.dialog
ovos_skill_cmd/locale/en-us/skill.json
ovos_skill_cmd/locale/eu/Run.voc
ovos_skill_cmd/locale/gl-es/Run.voc
ovos_skill_cmd/locale/gl-es/running.dialog
ovos_skill_cmd/locale/gl-es/skill.json
ovos_skill_cmd/locale/it-it/Run.voc
ovos_skill_cmd/locale/pt-pt/Run.voc
ovos_skill_cmd/locale/pt-pt/running.dialog
ovos_skill_cmd/locale/pt-pt/skill.json
ovos_skill_cmd/ovos_skill_cmd.egg-info/PKG-INFO
ovos_skill_cmd/ovos_skill_cmd.egg-info/SOURCES.txt
ovos_skill_cmd/ovos_skill_cmd.egg-info/dependency_links.txt
ovos_skill_cmd/ovos_skill_cmd.egg-info/entry_points.txt
ovos_skill_cmd/ovos_skill_cmd.egg-info/requires.txt
ovos_skill_cmd/ovos_skill_cmd.egg-info/top_level.txt
ovos_skill_cmd/test/test_plugin.py
ovos_skill_cmd/test/test_skill_loading.py
ovos_skill_cmd-0.2.11.dist-info/LICENSE.txt
ovos_skill_cmd-0.2.11.dist-info/METADATA
ovos_skill_cmd-0.2.11.dist-info/WHEEL
ovos_skill_cmd-0.2.11.dist-info/entry_points.txt
ovos_skill_cmd-0.2.11.dist-info/top_level.txt
ovos_skill_cmd-0.2.11.dist-info/RECORD
